anchor_survey-0.1.0.dist-info/licenses/LICENSE
gui/__init__.py
gui/survey_gui.py
survey/__init__.py
survey/survey.py
anchor_survey-0.1.0.dist-info/METADATA
anchor_survey-0.1.0.dist-info/WHEEL
anchor_survey-0.1.0.dist-info/top_level.txt
anchor_survey-0.1.0.dist-info/RECORD
