Metadata-Version: 2.4
Name: anchor_survey
Version: 0.1.0
Summary: Interactive tool for estimating seafloor anchor positions from ship survey data.
Author: Andrew Reed
License: BSD-3
Project-URL: Homepage, https://github.com/WHOIGit/anchor_survey
Project-URL: Issues, https://github.com/WHOIGit/anchor_survey/issues
Requires-Python: >=3.9
License-File: LICENSE
Requires-Dist: pandas
Requires-Dist: numpy
Requires-Dist: matplotlib
Requires-Dist: panel>=1.4.0
Dynamic: license-file
